yutipy/__init__.py
yutipy/base_clients.py
yutipy/deezer.py
yutipy/exceptions.py
yutipy/itunes.py
yutipy/kkbox.py
yutipy/lastfm.py
yutipy/logger.py
yutipy/models.py
yutipy/musicyt.py
yutipy/spotify.py
yutipy/cli/__init__.py
yutipy/cli/config.py
yutipy/cli/search.py
yutipy/utils/__init__.py
yutipy/utils/helpers.py
yutipy-5.0.1.dist-info/licenses/LICENSE
yutipy-5.0.1.dist-info/METADATA
yutipy-5.0.1.dist-info/WHEEL
yutipy-5.0.1.dist-info/entry_points.txt
yutipy-5.0.1.dist-info/top_level.txt
yutipy-5.0.1.dist-info/RECORD
