Metadata-Version: 2.4
Name: yutipy
Version: 5.0.1
Summary: A simple Python package to interact with various music platforms APIs.
Author: Cheap Nightbot
Author-email: Cheap Nightbot <hi@cheapnightbot.slmail.me>
Maintainer-email: Cheap Nightbot <hi@cheapnightbot.slmail.me>
License-Expression: MIT
Project-URL: Homepage, https://github.com/CheapNightbot/yutipy
Project-URL: Documentation, https://yutipy.readthedocs.io/
Project-URL: Repository, https://github.com/CheapNightbot/yutipy.git
Project-URL: Issues, https://github.com/CheapNightbot/yutipy/issues
Project-URL: Changelog, https://github.com/CheapNightbot/yutipy/blob/master/CHANGELOG.md
Project-URL: funding, https://ko-fi.com/cheapnightbot
Keywords: music,API,Deezer,iTunes,KKBox,Lastfm,Spotify,YouTube Music,search,retrieve,information,yutify
Classifier: Development Status :: 4 - Beta
Classifier: Intended Audience :: Developers
Classifier: Topic :: Software Development :: Libraries
Classifier: Programming Language :: Python :: 3
Classifier: Programming Language :: Python :: 3.10
Classifier: Programming Language :: Python :: 3.11
Classifier: Programming Language :: Python :: 3.12
Classifier: Operating System :: OS Independent
Requires-Python: >=3.10
License-File: LICENSE
Requires-Dist: python-dotenv>=1.2.1
Requires-Dist: requests>=2.32.5
Requires-Dist: ytmusicapi>=1.11.5
Dynamic: license-file
